better_exceptions_hook.pth
better_exceptions/__init__.py
better_exceptions/__main__.py
better_exceptions/color.py
better_exceptions/context.py
better_exceptions/encoding.py
better_exceptions/formatter.py
better_exceptions/log.py
better_exceptions/repl.py
better_exceptions/integrations/__init__.py
better_exceptions/integrations/django.py
better_exceptions-0.3.3.dist-info/LICENSE.txt
better_exceptions-0.3.3.dist-info/METADATA
better_exceptions-0.3.3.dist-info/WHEEL
better_exceptions-0.3.3.dist-info/top_level.txt
better_exceptions-0.3.3.dist-info/RECORD
